enpassant/__init__.py
enpassant/core.py
enpassant/ordereddict.py
enpassant-0.6.7.dist-info/DESCRIPTION.rst
enpassant-0.6.7.dist-info/METADATA
enpassant-0.6.7.dist-info/RECORD
enpassant-0.6.7.dist-info/WHEEL
enpassant-0.6.7.dist-info/metadata.json
enpassant-0.6.7.dist-info/top_level.txt
